evergrain/__init__.py
evergrain/core/discovery/engine.py
evergrain/core/enhancement/engine.py
evergrain/core/enhancement/filters.py
evergrain/core/enhancement/io.py
evergrain/core/enhancement/params.py
evergrain/core/exceptions/base.py
evergrain/core/exceptions/discovery.py
evergrain/core/exceptions/enhancement.py
evergrain/core/exceptions/segmentation.py
evergrain/core/metadata/assignment.py
evergrain/core/metadata/boundary_inference.py
evergrain/core/metadata/csv_loader.py
evergrain/core/metadata/engine.py
evergrain/core/metadata/normalization.py
evergrain/core/models/metadata.py
evergrain/core/models/segmentation.py
evergrain/core/segmentation/background.py
evergrain/core/segmentation/deskew.py
evergrain/core/segmentation/edge_detectors.py
evergrain/core/segmentation/engine.py
evergrain/core/segmentation/sampler.py
evergrain/utils/atomic.py
evergrain/utils/validators.py
evergrain-0.6.0.dist-info/WHEEL
evergrain-0.6.0.dist-info/METADATA
evergrain-0.6.0.dist-info/RECORD
