Metadata-Version: 2.3
Name: evergrain
Version: 0.6.0
Summary: Intelligent photo scanning and organization with automated cropping, enhancement, metadata embedding, and file renaming.
Requires-Dist: numpy>=2.4.0
Requires-Dist: opencv-python>=4.11.0.86
Requires-Dist: pillow>=12.0.0
Requires-Dist: psutil>=7.2.1
Requires-Python: >=3.12
